jax_finufft-1.2.0.dist-info/RECORD
jax_finufft-1.2.0.dist-info/WHEEL
jax_finufft-1.2.0.dist-info/METADATA
jax_finufft-1.2.0.dist-info/licenses/LICENSE
jax_finufft/options.py
jax_finufft/shapes.py
jax_finufft/lowering.py
jax_finufft/__init__.py
jax_finufft/ops.py
jax_finufft/jax_finufft_version.py
jax_finufft/jax_finufft_cpu.cpython-313-darwin.so
jax_finufft/include/finufft.h
jax_finufft/include/finufft_spread_opts.h
jax_finufft/include/finufft_errors.h
jax_finufft/include/finufft_opts.h
jax_finufft/include/finufft_eitherprec.h
jax_finufft/.dylibs/libc++abi.1.0.dylib
jax_finufft/.dylibs/libunwind.1.0.dylib
jax_finufft/.dylibs/libc++.1.0.dylib
jax_finufft/.dylibs/libomp.dylib
jax_finufft/lib/libfinufft.a
jax_finufft/share/licenses/finufft/LICENSE
jax_finufft/share/finufft/examples/simulplans1d1.cpp
jax_finufft/share/finufft/examples/simple1d1cf.c
jax_finufft/share/finufft/examples/simple1d1c.c
jax_finufft/share/finufft/examples/threadsafe1d1.cpp
jax_finufft/share/finufft/examples/guru1d1.cpp
jax_finufft/share/finufft/examples/guru1d1f.cpp
jax_finufft/share/finufft/examples/simple1d1.cpp
jax_finufft/share/finufft/examples/gurumany1d1.cpp
jax_finufft/share/finufft/examples/simple1d1f.cpp
jax_finufft/share/finufft/examples/spreadinterponly1d.cpp
jax_finufft/share/finufft/examples/many1d1.cpp
jax_finufft/share/finufft/examples/guru2d1.cpp
jax_finufft/share/finufft/examples/guru1d1c.c
jax_finufft/share/finufft/examples/threadsafe2d2f.cpp
jax_finufft/share/finufft/examples/simple2d1.cpp
