Metadata-Version: 2.1
Name: jax-finufft
Version: 1.2.0
Summary: JAX bindings for the Flatiron Institute Nonuniform Fast Fourier Transform library
Author-Email: Dan Foreman-Mackey <foreman.mackey@gmail.com>, Lehman Garrison <lgarrison@flatironinstitute.org>
License:                                  Apache License
Project-URL: Homepage, https://github.com/dfm/jax-finufft
Requires-Python: >=3.10
Requires-Dist: jax<0.8,>=0.5.0
Requires-Dist: numpy
Requires-Dist: pydantic>=2
Provides-Extra: test
Requires-Dist: pytest; extra == "test"
Requires-Dist: pytest-xdist; extra == "test"
Requires-Dist: absl-py; extra == "test"
Provides-Extra: cuda12
Requires-Dist: jax[cuda12]; extra == "cuda12"
Provides-Extra: cuda12-local
Requires-Dist: jax[cuda12-local]; extra == "cuda12-local"
